task3/f1_fsm.sv
module f1_fsm (
    input   logic       rst,
    input   logic       en,
    input   logic       clk,
    output  logic [7:0] data_out
);

    typedef enum {s0, s1, s2, s3, s4, s5, s6, s7, s8} my_state;
        my_state current_state, next_state;
        
    always_ff @(posedge clk, posedge rst)
        if (rst) current_state <= s0;
        else if (en)     current_state <= next_state;

    always_comb 
        case(current_state)
            s0: next_state = s1;
            s1: next_state = s2;
            s2: next_state = s3;
            s3: next_state = s4;
            s4: next_state = s5;
            s5: next_state = s6;
            s6: next_state = s7;
            s7: next_state = s8;
            s8: next_state = s0;
            default: next_state = s0;
        endcase
    
    always_comb
        case(current_state)
                s0: data_out = 8'b00000000;
                s1: data_out = 8'b00000001;
                s2: data_out = 8'b00000011;
                s3: data_out = 8'b00000111;
                s4: data_out = 8'b00001111;
                s5: data_out = 8'b00011111;
                s6: data_out = 8'b00111111;
                s7: data_out = 8'b01111111;
                s8: data_out = 8'b11111111;
                default: data_out = 8'b00000000;
        endcase

endmodule

task2/waveform.vcd
$version Generated by VerilatedVcd $end
$timescale 1ps $end
 $scope module TOP $end
  $var wire 1 # rst $end
  $var wire 1 $ en $end
  $var wire 1 % clk $end
  $var wire 8 & data_out [7:0] $end
  $scope module f1_fsm $end
   $var wire 1 # rst $end
   $var wire 1 $ en $end
   $var wire 1 % clk $end
   $var wire 8 & data_out [7:0] $end
   $var wire 32 ' current_state [31:0] $end
   $var wire 32 ( next_state [31:0] $end
  $upscope $end
 $upscope $end
$enddefinitions $end


#0
1#
1$
0%
b00000000 &
b00000000000000000000000000000000 '
b00000000000000000000000000000001 (
#1
1%
#2
0%
#3
1%
#4
0%
#5
1%
#6
0%
#7
1%
#8
0#
0%
#9
1%
b00000001 &
b00000000000000000000000000000001 '
b00000000000000000000000000000010 (
#10
0%
#11
1%
b00000011 &
b00000000000000000000000000000010 '
b00000000000000000000000000000011 (
#12
0%
#13
1%
b00000111 &
b00000000000000000000000000000011 '
b00000000000000000000000000000100 (
#14
0%
#15
1%
b00001111 &
b00000000000000000000000000000100 '
b00000000000000000000000000000101 (
#16
0%
#17
1%
b00011111 &
b00000000000000000000000000000101 '
b00000000000000000000000000000110 (
#18
0%
#19
1%
b00111111 &
b00000000000000000000000000000110 '
b00000000000000000000000000000111 (
#20
0%
#21
1%
b01111111 &
b00000000000000000000000000000111 '
b00000000000000000000000000001000 (
#22
0%
#23
1%
b11111111 &
b00000000000000000000000000001000 '
b00000000000000000000000000000000 (
#24
0%
#25
1%
b00000000 &
b00000000000000000000000000000000 '
b00000000000000000000000000000001 (
#26
0%
#27
1%
b00000001 &
b00000000000000000000000000000001 '
b00000000000000000000000000000010 (
